django_soft_delete/__init__.py
django_soft_delete/apps.py
django_soft_delete/models.py
django_soft_delete/tests/__init__.py
django_soft_delete/tests/models.py
django_soft_delete/tests/test_models.py
django_soft_delete/tests/migrations/0001_initial.py
django_soft_delete/tests/migrations/__init__.py
djangosoftdelete/__init__.py
djangosoftdelete/asgi.py
djangosoftdelete/settings.py
djangosoftdelete/urls.py
djangosoftdelete/wsgi.py
dj_soft_delete-1.0.1.dist-info/LICENSE
dj_soft_delete-1.0.1.dist-info/METADATA
dj_soft_delete-1.0.1.dist-info/WHEEL
dj_soft_delete-1.0.1.dist-info/top_level.txt
dj_soft_delete-1.0.1.dist-info/RECORD
